ndff/__init__.py
ndff/utils.py
ndff/api/__init__.py
ndff/api/api.py
ndff/api/object.py
ndff/connector/__init__.py
ndff/connector/connector.py
ndff/datasource/__init__.py
ndff/datasource/base.py
ndff/datasource/csv.py
ndff/datasource/postgres.py
ndff-0.1.3.dist-info/LICENSE
ndff-0.1.3.dist-info/METADATA
ndff-0.1.3.dist-info/WHEEL
ndff-0.1.3.dist-info/top_level.txt
ndff-0.1.3.dist-info/RECORD
