Metadata-Version: 2.1
Name: ndff
Version: 0.1.3
Summary: A package to interact with the Dutch NDFF-api
Home-page: https://gitlab.com/rduivenvoorde/ndff-connector
Author: Richard Duivenvoorde
Author-email: richard@zuidt.nl
License: GNU GENERAL PUBLIC LICENSE
Platform: UNKNOWN
License-File: LICENSE
Requires-Dist: requests
Requires-Dist: psycopg2
Requires-Dist: shapely
Provides-Extra: dev
Requires-Dist: sphinx ; extra == 'dev'
Provides-Extra: test
Requires-Dist: pytest ; extra == 'test'
